etawatch/__init__.py
etawatch/etawatch.py
etawatch-1.1.3.dist-info/LICENSE
etawatch-1.1.3.dist-info/METADATA
etawatch-1.1.3.dist-info/WHEEL
etawatch-1.1.3.dist-info/top_level.txt
etawatch-1.1.3.dist-info/RECORD
