Metadata-Version: 2.1
Name: etawatch
Version: 1.1.3
Summary: Like a stopwatch, but it also gives you an ETA
Author-email: "Rick D. Gray" <rickdgray@outlook.com>
License: GNU GENERAL PUBLIC LICENSE
Project-URL: Homepage, https://github.com/rickdgray/etawatch
Classifier: Programming Language :: Python :: 3
Classifier: License :: OSI Approved :: GNU General Public License v3 (GPLv3)
Classifier: Operating System :: OS Independent
Classifier: Development Status :: 5 - Production/Stable
Classifier: Topic :: Utilities
Requires-Python: >=3.7
License-File: LICENSE
